DESCRIPTION.rst
MANIFEST.in
README.md
RELEASE-VERSION
setup.cfg
setup.py
version.py
bioshake_device/__init__.py
bioshake_device/bioshake_device.py
bioshake_device.egg-info/PKG-INFO
bioshake_device.egg-info/SOURCES.txt
bioshake_device.egg-info/dependency_links.txt
bioshake_device.egg-info/requires.txt
bioshake_device.egg-info/top_level.txt