Metadata-Version: 1.1
Name: bioshake-device
Version: 1.7
Summary: Interface to Q.instruments BioShake devices.
Home-page: https://github.com/janelia-pypi/bioshake_device_python
Author: Peter Polidoro
Author-email: polidorop@janelia.hhmi.org
License: BSD
Keywords: bioshake serial device
Platform: UNKNOWN
Classifier: Development Status :: 4 - Beta
Classifier: Intended Audience :: Developers
Classifier: Topic :: Software Development :: Build Tools
Classifier: License :: OSI Approved :: BSD License
Classifier: Programming Language :: Python :: 2.7
